huge_test_hive_ti_client/__init__.py
huge_test_hive_ti_client/api_client.py
huge_test_hive_ti_client/api_response.py
huge_test_hive_ti_client/configuration.py
huge_test_hive_ti_client/exceptions.py
huge_test_hive_ti_client/py.typed
huge_test_hive_ti_client/rest.py
huge_test_hive_ti_client/api/__init__.py
huge_test_hive_ti_client/api/pet_api.py
huge_test_hive_ti_client/api/store_api.py
huge_test_hive_ti_client/api/user_api.py
huge_test_hive_ti_client/models/__init__.py
huge_test_hive_ti_client/models/address.py
huge_test_hive_ti_client/models/api_response.py
huge_test_hive_ti_client/models/category.py
huge_test_hive_ti_client/models/customer.py
huge_test_hive_ti_client/models/order.py
huge_test_hive_ti_client/models/pet.py
huge_test_hive_ti_client/models/tag.py
huge_test_hive_ti_client/models/user.py
huge_test_hive_ti_client-1.0.0.dist-info/METADATA
huge_test_hive_ti_client-1.0.0.dist-info/WHEEL
huge_test_hive_ti_client-1.0.0.dist-info/top_level.txt
huge_test_hive_ti_client-1.0.0.dist-info/RECORD
